pygempick/__init__.py
pygempick/core.py
pygempick/modeling.py
pygempick/spatialstats.py
pygempick-1.2.0.dist-info/DESCRIPTION.rst
pygempick-1.2.0.dist-info/METADATA
pygempick-1.2.0.dist-info/RECORD
pygempick-1.2.0.dist-info/WHEEL
pygempick-1.2.0.dist-info/metadata.json
pygempick-1.2.0.dist-info/top_level.txt
