Metadata-Version: 2.0
Name: pygempick
Version: 1.2.0
Summary: Open Source Batch Gold Particle Picking & Procesing for Immunogold Diagnostics
Home-page: https://github.com/jmarsil/pygempick
Author: Joseph Marsilla
Author-email: joseph.marsilla@mail.utoronto.ca
License: MIT
Keywords: immunogold batch gold particle picker EM micrograph processing correlation       analysis IGEM diagnostics
Platform: UNKNOWN
Classifier: Development Status :: 3 - Alpha
Classifier: License :: OSI Approved :: MIT License
Classifier: Programming Language :: Python :: 3.6
Classifier: Intended Audience :: Developers
Classifier: Intended Audience :: Education
Classifier: Intended Audience :: End Users/Desktop
Classifier: Intended Audience :: Science/Research
Classifier: Operating System :: MacOS
Classifier: Operating System :: Unix
Classifier: Topic :: Education
Classifier: Topic :: Utilities
Classifier: Topic :: Software Development :: Libraries :: Python Modules
Classifier: Topic :: Scientific/Engineering :: Mathematics
Requires-Dist: numpy
Requires-Dist: pandas
Requires-Dist: matplotlib
Requires-Dist: opencv-python
